LICENSE.txt
MANIFEST.in
README
README.rst
requirements.txt
setup.py
AdvancedSearchDiscovery.egg-info/PKG-INFO
AdvancedSearchDiscovery.egg-info/SOURCES.txt
AdvancedSearchDiscovery.egg-info/dependency_links.txt
AdvancedSearchDiscovery.egg-info/entry_points.txt
AdvancedSearchDiscovery.egg-info/pbr.json
AdvancedSearchDiscovery.egg-info/top_level.txt
asd/__init__.py
asd/info.py
asd/run.py